akello_apps/__init__.py
akello_apps/base.py
akello_apps/client.py
akello_apps/_template_app/README.md
akello_apps/_template_app/__init__.py
akello_apps/_template_app/client.py
akello_apps/_template_app/plugin.py
akello_apps/_template_app/webhooks/__init__.py
akello_apps/advancedMD/__init__.py
akello_apps/advancedMD/client.py
akello_apps/advancedMD/tests/__init__.py
akello_apps/aws_ses/README.md
akello_apps/aws_ses/__init__.py
akello_apps/aws_ses/client.py
akello_apps/aws_ses/plugin.py
akello_apps/aws_ses/webhooks/__init__.py
akello_apps/fhir_risk_score/README.md
akello_apps/fhir_risk_score/__init__.py
akello_apps/fhir_risk_score/client.py
akello_apps/fhir_risk_score/plugin.py
akello_apps/fhir_risk_score/tests/__init__.py
akello_apps/fhir_risk_score/tests/synthea_data_andrea_jenkins.json
akello_apps/fhir_risk_score/tests/test_fhir_score.py
akello_apps/fhir_risk_score/webhooks/__init__.py
akello_apps/metriport/README.md
akello_apps/metriport/__init__.py
akello_apps/metriport/client.py
akello_apps/metriport/plugin.py
akello_apps/metriport/webhooks/__init__.py
akello_apps/metriport/webhooks/metriport_webhook.py
akello_apps/sendgrid/README.md
akello_apps/sendgrid/__init__.py
akello_apps/sendgrid/client.py
akello_apps/sendgrid/plugin.py
akello_apps/sendgrid/webhooks/__init__.py
akello_apps/typeform/README.md
akello_apps/typeform/__init__.py
akello_apps/typeform/client.py
akello_apps/typeform/plugin.py
akello_apps/typeform/screeners/__init__.py
akello_apps/typeform/screeners/phq9.yaml
akello_apps/typeform/tests/__init__.py
akello_apps/typeform/tests/sample-phq9.json
akello_apps/typeform/tests/test_typeform.py
akello_apps/typeform/webhooks/__init__.py
akello_apps/typeform/webhooks/typeform_webhook.py
akello_apps-0.0.1.dist-info/METADATA
akello_apps-0.0.1.dist-info/WHEEL
akello_apps-0.0.1.dist-info/RECORD
